<?xml version="1.0" encoding="UTF-8"?>
<fakulta děkan="Jakub Moravec">
  <katedra zkratka_katedry="KI" webové_stránky="ki.ujep.cz">
    <vedoucí>
      <jméno>Jakub Moravec</jméno>
      <telefon>+420704128130</telefon>
    </vedoucí>
    <zaměstnanci>
      <zaměstnanec>
        <jméno>Jakub Moravec</jméno>
        <telefon>+420704128130</telefon>
        <email>kubik.moravec@email.cz</email>
        <pozice>
          <odborný_asistent/>
        </pozice>
      </zaměstnanec>
    </zaměstnanci>
    <předměty>
      <předmět zkratka="PRI">
        <název>Prográmko pro internet</název>
        <popis>srandy kopec</popis>
      </předmět>
    </předměty>
  </katedra>
</fakulta>
